.coveragerc
CHANGES.rst
MANIFEST.in
Makefile
README.rst
bootstrap.py
buildout.cfg
setup.py
tox.ini
src/cipher/__init__.py
src/cipher.logview.egg-info/PKG-INFO
src/cipher.logview.egg-info/SOURCES.txt
src/cipher.logview.egg-info/dependency_links.txt
src/cipher.logview.egg-info/entry_points.txt
src/cipher.logview.egg-info/not-zip-safe
src/cipher.logview.egg-info/requires.txt
src/cipher.logview.egg-info/top_level.txt
src/cipher/logview/__init__.py
src/cipher/logview/decorators.py
src/cipher/logview/middleware.py
src/cipher/logview/pagetemplate.py
src/cipher/logview/publication.py
src/cipher/logview/stackformatter.py
src/cipher/logview/testing.py
src/cipher/logview/tests/__init__.py
src/cipher/logview/tests/nested.pt
src/cipher/logview/tests/sample.pt
src/cipher/logview/tests/test_decorators.py
src/cipher/logview/tests/test_middleware.py
src/cipher/logview/tests/test_pagetemplate.py
src/cipher/logview/tests/test_publication.py
src/cipher/logview/tests/test_stackformatter.py