Metadata-Version: 1.1
Name: cipher.logview
Version: 1.1.0
Summary: WSGI middleware that shows you log messages produced during request handling.
Home-page: https://github.com/CipherHealth/cipher.logview
Author: CipherHealth LLC
Author-email: dev@cipherhealth.com
License: MIT
Platform: UNKNOWN
Classifier: Development Status :: 4 - Beta
Classifier: Environment :: Web Environment
Classifier: Intended Audience :: Developers
Classifier: Programming Language :: Python :: 2.6
Classifier: Programming Language :: Python :: 2.7
Classifier: Programming Language :: Python :: 3.3
Classifier: Natural Language :: English
Classifier: Operating System :: OS Independent
Classifier: Topic :: Internet :: WWW/HTTP
Classifier: Framework :: Zope3
